dead_code_finder/Makefile
dead_code_finder/__init__.py
dead_code_finder/cli.py
dead_code_finder/tests/module_a.py
dead_code_finder/tests/module_b.py
dead_code_finder/tests/test_dead_code_finder.py
dead_code_finder/tests/test_case1/hello_world.py
dead_code_finder/tests/test_case1/subdir/one_more_file.py
dead_code_finder/tests/test_case1/subdir/another_subdir/__init__.py
dead_code_finder-0.0.3.dist-info/METADATA
dead_code_finder-0.0.3.dist-info/WHEEL
dead_code_finder-0.0.3.dist-info/entry_points.txt
dead_code_finder-0.0.3.dist-info/RECORD
